fastnorm/__init__.py
fastnorm/bvnorm.py
fastnorm/util.py
fastnorm-25.11.1.dist-info/licenses/LICENSE
fastnorm-25.11.1.dist-info/WHEEL
fastnorm-25.11.1.dist-info/METADATA
fastnorm-25.11.1.dist-info/RECORD
