Metadata-Version: 2.4
Name: fastnorm
Version: 25.11.1
Summary: Fast evaluation of multivariate normal distribution
Keywords: statistics
Author: Martin van der Schans
Requires-Python: >=3.9
License-File: LICENSE
Requires-Dist: numpy
Requires-Dist: pandas
Requires-Dist: statsmodels
Project-URL: repository, https://github.com/mvds314/fastnorm
